{"use_content_hash":false,"mappings":{"6.AppleScript/8.ReferenceForms/3.Filter.html":[[51],495672766,[]],"6.AppleScript/6.ClassReference/17.text.html":[[59],1269943189,[]],"6.AppleScript/9.OperatorsReference/index.html":[[79],4222378784,[]],"3.rust/2所有权.html":[[15],4274926197,[]],"5.typescript/jtest测试框架/Globals.html":[[28],1011909070,[]],"4.groovy/开发工具类.html":[[35],2353867131,[]],"6.AppleScript/4.ScriptObjects/3.SendingCommandsToScriptObjects.html":[[83],4094249386,[]],"6.AppleScript/6.ClassReference/2.application.html":[[73],3037504764,[]],"6.AppleScript/8.ReferenceForms/6.Middle.html":[[50],1855505137,[]],"3.rust/rust指针.html":[[0],3689364241,[]],"1.C++/C++与C的区别.html":[[38],417926379,[]],"6.AppleScript/8.ReferenceForms/index.html":[[49],2676000530,[]],"3.rust/rust执行shell命令.html":[[19],265713558,[]],"3.rust/rfcs/0911-const-fn.html":[[2],3193658210,[]],"6.AppleScript/6.ClassReference/8.integer.html":[[60],179578563,[]],"6.AppleScript/2.AppleScriptFundamentals/4.CommandsOverview.html":[[95],1142219039,[]],"6.AppleScript/8.ReferenceForms/7.Name.html":[[56],1855505137,[]],"3.rust/结构体.html":[[5],3444098093,[]],"6.AppleScript/3.VariablesAndProperties/1.DefiningProperties.html":[[46],2721308545,[]],"3.rust/Rust中的Sizedness.html":[[17],2093344985,[]],"6.AppleScript/index.html":[[58],2607960582,[]],"3.rust/newType模式.html":[[6],265713558,[]],"6.AppleScript/2.AppleScriptFundamentals/5.GlobalConstantsInAppleScript.html":[[94],1142219039,[]],"2.LUA/index.html":[[20],2380115258,[]],"6.AppleScript/3.VariablesAndProperties/3.ScopeOfVariablesAndProperties.html":[[45],1979880198,[]],"6.AppleScript/6.ClassReference/16.script.html":[[61],3969063005,[]],"3.rust/rust面向对象特性.html":[[16],2598557255,[]],"3.rust/函数式编程.html":[[10],1322490560,[]],"3.rust/ConstantsAndVariables.html":[[9],721387250,[]],"5.typescript/1.基础类型.html":[[25],3665280848,[]],"3.rust/迭代与闭包.html":[[14],3444098093,[]],"5.typescript/jtest测试框架/Except.html":[[31],3898723657,[]],"4.groovy/基础语法.html":[[34],728758963,[]],"6.AppleScript/8.ReferenceForms/1.Arbitrary.html":[[52],3384414521,[]],"6.AppleScript/6.ClassReference/5.constant.html":[[62],3733285444,[]],"6.AppleScript/6.ClassReference/3.boolean.html":[[63],3037504764,[]],"5.typescript/4.模块.html":[[23],2841911327,[]],"5.typescript/jtest测试框架/index.html":[[30],2841911327,[]],"3.rust/模式匹配.html":[[1],1035994511,[]],"6.AppleScript/6.ClassReference/12.real.html":[[65],2041035148,[]],"6.AppleScript/6.ClassReference/6.date.html":[[70],3733285444,[]],"6.AppleScript/2.AppleScriptFundamentals/7.AliasesAndFiles.html":[[86],2418388376,[]],"6.AppleScript/CommonUse.html":[[42],2607960582,[]],"6.AppleScript/8.ReferenceForms/5.Index.html":[[53],3131674230,[]],"3.rust/rfcs/0195_associated-items.html":[[3],3193658210,[]],"6.AppleScript/2.AppleScriptFundamentals/8.RemoteApplications.html":[[87],3508551886,[]],"6.AppleScript/4.ScriptObjects/4.ScriptLibraries.html":[[82],1395366498,[]],"3.rust/const类型与函数.html":[[12],2834605150,[]],"6.AppleScript/6.ClassReference/index.html":[[66],305035060,[]],"6.AppleScript/2.AppleScriptFundamentals/2.Coercion(ObjectConversion).html":[[90],3811979991,[]],"6.AppleScript/2.AppleScriptFundamentals/9.ErrorHanding.html":[[92],3508551886,[]],"6.AppleScript/2.AppleScriptFundamentals/1.ObjectSpecifiers.html":[[96],923237968,[]],"6.AppleScript/6.ClassReference/7.file.html":[[76],179578563,[]],"6.AppleScript/5.AboutHandlers/1.HandlerBasics.html":[[99],2266683109,[]],"6.AppleScript/8.ReferenceForms/9.Range.html":[[54],798830503,[]],"5.typescript/index.html":[[24],239530967,[]],"6.AppleScript/2.AppleScriptFundamentals/6.ITAndMe.html":[[91],2418388376,[]],"4.groovy/操作符.html":[[33],1484547580,[]],"6.AppleScript/5.AboutHandlers/3.CallingAScriptApplicationFromAScript.html":[[100],3323935667,[]],"5.typescript/3.接口.html":[[26],2102750360,[]],"6.AppleScript/8.ReferenceForms/10.Relative.html":[[55],4222378784,[]],"6.AppleScript/5.AboutHandlers/2.HandlersInScriptApplications.html":[[101],3323935667,[]],"3.rust/常见集合.html":[[18],3924904200,[]],"2.LUA/基本语法.html":[[22],2380115258,[]],"1.C++/C++面向对象.html":[[41],417926379,[]],"3.rust/1常见编程概念.html":[[11],4274926197,[]],"4.groovy/编程结构.html":[[36],239530967,[]],"6.AppleScript/3.VariablesAndProperties/index.html":[[44],85003337,[]],"6.AppleScript/6.ClassReference/9.list.html":[[67],2912351499,[]],"6.AppleScript/6.ClassReference/18.unitTypes.html":[[69],1269943189,[]],"6.AppleScript/6.ClassReference/15.RGBcolor.html":[[75],3969063005,[]],"6.AppleScript/6.ClassReference/11.POSIXfile.html":[[68],2041035148,[]],"5.typescript/jtest测试框架/Hook顺序.html":[[29],1011909070,[]],"6.AppleScript/2.AppleScriptFundamentals/10.DebuggingAppleScripts.html":[[88],85003337,[]],"6.AppleScript/6.ClassReference/1.alias.html":[[77],305035060,[]],"6.AppleScript/2.AppleScriptFundamentals/3.ScriptingAdditions.html":[[93],3811979991,[]],"6.AppleScript/6.ClassReference/13.record.html":[[74],950162650,[]],"3.rust/泛型与trait.html":[[13],427395242,[]],"2.LUA/高级语法.html":[[21],1508696509,[]],"5.typescript/2.变量声明.html":[[27],3665280848,[]],"3.rust/依赖管理.html":[[7],2598557255,[]],"index.html":[[37],3217809187,[]],"6.AppleScript/6.ClassReference/10.number.html":[[72],2912351499,[]],"6.AppleScript/4.ScriptObjects/1.DefiningScriptObjects.html":[[81],540542253,[]],"6.AppleScript/4.ScriptObjects/index.html":[[84],1979880198,[]],"6.AppleScript/1.AppleScriptLexicalConventions/index.html":[[97],1329798785,[]],"6.AppleScript/8.ReferenceForms/8.Property.html":[[48],798830503,[]],"6.AppleScript/4.ScriptObjects/2.InitializingScriptObjects.html":[[80],4094249386,[]],"6.AppleScript/5.AboutHandlers/index.html":[[98],2266683109,[]],"6.AppleScript/6.ClassReference/14.reference.html":[[71],950162650,[]],"6.AppleScript/7.CommandsReference/index.html":[[78],2676000530,[]],"6.AppleScript/4.ScriptObjects/5.InheritanceInScriptObjects.html":[[85],1395366498,[]],"6.AppleScript/3.VariablesAndProperties/2.DeclaringVariables.html":[[43],2721308545,[]],"6.AppleScript/6.ClassReference/4.class.html":[[64],1631447163,[]],"6.AppleScript/2.AppleScriptFundamentals/index.html":[[89],1329798785,[]],"6.AppleScript/8.ReferenceForms/4.ID.html":[[57],3131674230,[]],"6.AppleScript/8.ReferenceForms/2.Every.html":[[47],495672766,[]],"4.groovy/RuntimeAndCompile-timeMetaprogramming.html":[[32],4284397108,[]],"1.C++/cmake/index.html":[[39],3436724332,[]],"3.rust/Rust库API设计文档规范.html":[[4],2093344985,[]],"1.C++/泛型编程.html":[[40],3436724332,[]],"3.rust/宏.html":[[8],3924904200,[]]},"last_pl_number":0,"num_deleted_docs":0,"pl_names_to_cache":[0]}